{
    "AWSEBDockerrunVersion": 2,
    "containerDefinitions": [
        {
            "name": "client",
            "image": "adityakadu12/multi-client",
            "hostname": "client",
            "essential": false
        },
        {
            "name": "server",
            "image": "adityakadu12/multi-server",
            "hostname": "api",
            "essential": false
        },
        {
            "name": "worker",
            "image": "adityakadu12/multi-worker",
            "hostname": "worker",
            "essential": false
        },
        {
            "name": "nginx",
            "image": "adityakadu12/multi-nginx",
            "hostname": "nginx",
            "essential": true,
            "portMappings":[
                {
                    "hostPort": 80,
                    "containerPort": 80
                }

            ],
            "links": ["client", "server"]
        }

    ]
}